funcattr.py
funcattr-0.0.0.dist-info/LICENSE.txt
funcattr-0.0.0.dist-info/WHEEL
funcattr-0.0.0.dist-info/METADATA
funcattr-0.0.0.dist-info/RECORD
