Metadata-Version: 2.1
Name: funcattr
Version: 0.0.0
Summary: Assign attributes to functions using a decorator.
Author-email: Kale Kundert <kale@thekunderts.net>
Requires-Dist: pytest ; extra == "test"
Project-URL: Bug Tracker, https://github.com/kalekundert/funcattr/issues
Project-URL: Continuous Integration, https://github.com/kalekundert/funcattr/actions
Project-URL: Documentation, https://funcattr.readthedocs.io/en/latest/
Project-URL: Test Coverage, https://coveralls.io/github/kalekundert/funcattr
Project-URL: Version Control, https://github.com/kalekundert/funcattr
Provides-Extra: test
